sefr_cut/SEFR_CUT.py
sefr_cut/__init__.py
sefr_cut/extract_features.py
sefr_cut/preprocessing.py
sefr_cut/deepcut/__init__.py
sefr_cut/deepcut/deepcut.py
sefr_cut/deepcut/model.py
sefr_cut/deepcut/stop_words.py
sefr_cut/deepcut/train.py
sefr_cut/deepcut/utils.py
sefr_cut/deepcut/weight/cnn_without_ne_ab.h5
sefr_cut/model/crf_best_entropyfrom_dc_bl_full_socialDict.model
sefr_cut/model/crf_tnhc_entropyfrom_dc_bl_full_socialDict.model
sefr_cut/model/crf_ws1000_entropyfrom_dc_bl_full_socialDict.model
sefr_cut/model/my_model.model
sefr_cut/variable/words_modified.txt
sefr_cut/weight/model_weight_best.h5
sefr_cut/weight/model_weight_tnhc.h5
sefr_cut/weight/model_weight_ws1000.h5
SEFR_CUT-1.1.dist-info/LICENSE
SEFR_CUT-1.1.dist-info/METADATA
SEFR_CUT-1.1.dist-info/WHEEL
SEFR_CUT-1.1.dist-info/top_level.txt
SEFR_CUT-1.1.dist-info/RECORD
