Metadata-Version: 2.1
Name: SEFR-CUT
Version: 1.1
Summary: Domain Adaptation of Thai Word Segmentation Models using Stacked Ensemble (EMNLP2020)
Home-page: https://github.com/mrpeerat/SEFR_CUT
Author: mrpeerat
Author-email: peerat.l_s19@vistec.ac.th
License: MIT
Keywords: thai word segmentation,word segmentation,thainlp
Platform: UNKNOWN
Classifier: Development Status :: 5 - Production/Stable
Classifier: Natural Language :: Thai
Classifier: License :: OSI Approved :: MIT License
Classifier: Topic :: Text Processing :: Linguistic
Requires-Dist: tensorflow (>=2.0.0)
Requires-Dist: pandas
Requires-Dist: scipy
Requires-Dist: numpy
Requires-Dist: scikit-learn
Requires-Dist: python-crfsuite
Requires-Dist: pyahocorasick
